[{"language": "hi", "buddyIds": "", "appName": "AstRoamer_Element_Hunt_Activity", "userId": "216314", "sessionId": "n1al5t10swhd5mn9nzt5reggvgq4dvjx", "appData": {"event_type": "game_start", "language": "hi"}, "createdAt": "2018-8-25 10:41:31"}, {"appData": {"language": "hi", "Currentclue": "\u0938\u0902\u0915\u0947\u0924 1", "event_type": "clue_end", "NumberofAttempts": 1, "FirstAttemptAnswer": -177.60000000000267}, "language": "hi", "appName": "AstRoamer_Element_Hunt_Activity", "userId": "216314", "sessionId": "n1al5t10swhd5mn9nzt5reggvgq4dvjx", "buddyIds": "", "createdAt": "2018-8-25 10:43:24"}, {"buddyIds": "", "appData": {"Currentclue": "\u0938\u0902\u0915\u0947\u0924 2", "event_type": "clue_end", "language": "hi", "FirstAttemptAnswer": 110.79999999999666, "NumberofAttempts": 2, "SecondAttemptAnswer": 133.19999999999538}, "appName": "AstRoamer_Element_Hunt_Activity", "userId": "216314", "language": "hi", "sessionId": "n1al5t10swhd5mn9nzt5reggvgq4dvjx", "createdAt": "2018-8-25 10:44:44"}, {"language": "hi", "buddyIds": "", "appName": "AstRoamer_Element_Hunt_Activity", "userId": "216314", "sessionId": "n1al5t10swhd5mn9nzt5reggvgq4dvjx", "appData": {"language": "hi", "Currentclue": "\u0938\u0902\u0915\u0947\u0924  3", "event_type": "clue_end", "NumberofAttempts": 1, "FirstAttemptAnswer": 62.40000000000299}, "createdAt": "2018-8-25 10:45:29"}, {"appData": {"Currentclue": "\u0938\u0902\u0915\u0947\u0924 4", "event_type": "clue_end", "language": "hi", "FirstAttemptAnswer": 31.59999999999792, "NumberofAttempts": 2, "SecondAttemptAnswer": -82.00000000000614}, "language": "hi", "appName": "AstRoamer_Element_Hunt_Activity", "userId": "216314", "sessionId": "n1al5t10swhd5mn9nzt5reggvgq4dvjx", "buddyIds": "", "createdAt": "2018-8-25 10:46:57"}, {"buddyIds": "", "appData": {"language": "hi", "Currentclue": "\u0938\u0902\u0915\u0947\u0924 5", "event_type": "clue_end", "NumberofAttempts": 1, "FirstAttemptAnswer": -57.19999999999871}, "appName": "AstRoamer_Element_Hunt_Activity", "userId": "216314", "language": "hi", "sessionId": "n1al5t10swhd5mn9nzt5reggvgq4dvjx", "createdAt": "2018-8-25 10:47:42"}, {"language": "hi", "buddyIds": "", "appName": "AstRoamer_Element_Hunt_Activity", "userId": "216314", "sessionId": "n1al5t10swhd5mn9nzt5reggvgq4dvjx", "appData": {"Currentclue": "\u0938\u0902\u0915\u0947\u0924 6", "event_type": "clue_end", "language": "hi", "FirstAttemptAnswer": -122.40000000000659, "NumberofAttempts": 2, "SecondAttemptAnswer": -8.800000000005127}, "createdAt": "2018-8-25 10:49:3"}, {"appData": {"event_type": "game_start", "language": "hi"}, "language": "hi", "appName": "AstRoamer_Element_Hunt_Activity", "userId": "216314", "sessionId": "hpvcm01ms55zs9res8m5qx3wljg8472o", "buddyIds": "", "createdAt": "2018-8-25 11:2:23"}, {"buddyIds": "", "appData": {"Currentclue": "\u0938\u0902\u0915\u0947\u0924 1", "event_type": "clue_end", "language": "hi", "FirstAttemptAnswer": 110.40000000000123, "NumberofAttempts": 2, "SecondAttemptAnswer": -65.59999999999883}, "appName": "AstRoamer_Element_Hunt_Activity", "userId": "216314", "language": "hi", "sessionId": "hpvcm01ms55zs9res8m5qx3wljg8472o", "createdAt": "2018-8-25 11:5:49"}, {"language": "hi", "buddyIds": "", "appName": "AstRoamer_Element_Hunt_Activity", "userId": "216314", "sessionId": "hpvcm01ms55zs9res8m5qx3wljg8472o", "appData": {"Currentclue": "\u0938\u0902\u0915\u0947\u0924 2", "event_type": "clue_end", "language": "hi", "FirstAttemptAnswer": 95.20000000000005, "NumberofAttempts": 2, "SecondAttemptAnswer": 145.1999999999972}, "createdAt": "2018-8-25 11:6:23"}, {"appData": {"Currentclue": "\u0938\u0902\u0915\u0947\u0924  3", "event_type": "clue_end", "language": "hi", "FirstAttemptAnswer": -68.00000000000098, "NumberofAttempts": 2, "SecondAttemptAnswer": -146.4000000000022}, "language": "hi", "appName": "AstRoamer_Element_Hunt_Activity", "userId": "216314", "sessionId": "hpvcm01ms55zs9res8m5qx3wljg8472o", "buddyIds": "", "createdAt": "2018-8-25 11:7:10"}, {"buddyIds": "", "appData": {"Currentclue": "\u0938\u0902\u0915\u0947\u0924 4", "event_type": "clue_end", "language": "hi", "FirstAttemptAnswer": -57.20000000000334, "NumberofAttempts": 2, "SecondAttemptAnswer": -4.400000000002592}, "appName": "AstRoamer_Element_Hunt_Activity", "userId": "216314", "language": "hi", "sessionId": "hpvcm01ms55zs9res8m5qx3wljg8472o", "createdAt": "2018-8-25 11:8:19"}, {"language": "hi", "buddyIds": "", "appName": "AstRoamer_Element_Hunt_Activity", "userId": "216314", "sessionId": "hpvcm01ms55zs9res8m5qx3wljg8472o", "appData": {"Currentclue": "\u0938\u0902\u0915\u0947\u0924 5", "event_type": "clue_end", "language": "hi", "FirstAttemptAnswer": -33.19999999999837, "NumberofAttempts": 2, "SecondAttemptAnswer": -49.5999999999986}, "createdAt": "2018-8-25 11:9:23"}, {"appData": {"language": "hi", "Currentclue": "\u0938\u0902\u0915\u0947\u0924 6", "event_type": "clue_end", "NumberofAttempts": 1, "FirstAttemptAnswer": -68.40000000000596}, "language": "hi", "appName": "AstRoamer_Element_Hunt_Activity", "userId": "216314", "sessionId": "hpvcm01ms55zs9res8m5qx3wljg8472o", "buddyIds": "", "createdAt": "2018-8-25 11:10:30"}]